Metadata-Version: 2.1
Name: spps-py
Version: 1.0.0rc1
Summary: Simple Password Protection Solution for Python
Home-page: https://github.com/elomagic/spps-py
Author: Carsten Rambow
Author-email: spps.dev@elomagic.de
License: Apache-2.0
Project-URL: Source, https://github.com/elomagic/spps-py
Project-URL: Tracker, https://github.com/elomagic/spps-py/issues
Keywords: encrypt,decrypt,password,security,hide,protect,key,secret,AES,GCM
Platform: UNKNOWN
Classifier: Development Status :: 3 - Alpha
Classifier: Intended Audience :: Developers
Classifier: License :: OSI Approved :: Apache Software License
Classifier: Programming Language :: Python :: 3.9
Classifier: Topic :: Security
Classifier: Topic :: Security :: Cryptography
Classifier: Topic :: Software Development
Requires-Python: >=3.9
License-File: LICENSE.txt
